{
    "title": [
        "Charles I"
    ],
    "Born": [
        "19 November 1600 , Dunfermline Palace, Dunfermline, Scotland"
    ],
    "Died": [
        "30 January 1649(1649-01-30) (aged 48) , Whitehall, London"
    ],
    "Burial": [
        "9 February 1649 , St George's Chapel, Windsor Castle, England"
    ],
    "Spouse": [
        "Henrietta Maria of France ( m. 1625)"
    ],
    "IssueDetail": [
        "Charles James, Duke of Cornwall",
        "Charles II",
        "Mary, Princess of Orange",
        "James II & VII",
        "Elizabeth",
        "Anne",
        "Catherine",
        "Henry, Duke of Gloucester",
        "Henrietta, Duchess of Orleans"
    ],
    "House": [
        "Stuart"
    ],
    "Father": [
        "James VI of Scotland and I of England"
    ],
    "Mother": [
        "Anne of Denmark"
    ],
    "Religion": [
        "Anglican"
    ]
}