{
    "title": [
        "Brigitte Nielsen"
    ],
    "Born": [
        "Gitte Nielsen ,  (1963-07-15) 15 July 1963 (age 55) , R\u00f8dovre, Denmark"
    ],
    "Occupation": [
        "Actress, model, singer"
    ],
    "Years active": [
        "1984-present"
    ],
    "Spouse(s)": [
        "Kasper Winding ( m. 1983-1984) , Sylvester Stallone , ( m. 1985;  div. 1987) , Sebastian Copeland ( m. 1990-1992) , Raoul Meyer ( m. 1993-2005) , Mattia Dessi ( m. 2006)"
    ],
    "Partner(s)": [
        "Mark Gastineau (1988-1990) , Flavor Flav (2005)"
    ],
    "Children": [
        "5"
    ]
}