{
  "title": [
    "Eugene Polley"
  ],
  "Born": [
    "Eugene J. Polley  November 29, 1915  Chicago, Illinois, USA"
  ],
  "Died": [
    "May 20, 2012 (aged 96)  Downers Grove, Illinois"
  ],
  "Education": [
    "City Colleges of Chicago, Armour Institute of Technology"
  ],
  "Occupation": [
    "Engineer"
  ],
  "Discipline": [
    "Engineering"
  ],
  "Employer(s)": [
    "Zenith Electronics   1935 - 1982"
  ],
  "Projects": [
    "Radar",
    " Push-button car radio",
    " Video disks"
  ],
  "Significant design": [
    "Wireless remote control for televisions"
  ],
  "Awards": [
    "Technology & Engineering Emmy Award (1997) ",
    " IEEE Consumer Electronics Award (2009)"
  ]
}