{
  "title": [
    "Far East Movement"
  ],
  "Origin": [
    "Los Angeles, California, United States"
  ],
  "Genres": [
    "Hip hop ",
    " pop ",
    " EDM"
  ],
  "Years active": [
    "2003 - present"
  ],
  "Labels": [
    "Cherrytree ",
    " Interscope ",
    " Delicious Deli ",
    " Spinnin' ",
    " Transparent Agency ",
    "  E1"
  ],
  "Associated acts": [
    "Stereotypes ",
    " Flo Rida ",
    " Sidney Samson ",
    " Cherry Cherry Boom Boom ",
    " Jin ",
    " Ken Oak ",
    " The Cataracs ",
    " Dev ",
    " Ryan Tedder ",
    " Snoop Dogg ",
    " Frankmusik ",
    " Colette Carr ",
    " Natalia Kills ",
    " Cover Drive ",
    " Justin Bieber ",
    " Redfoo ",
    " Riff Raff ",
    " Skrillex ",
    " Diplo ",
    " Afrojack ",
    " Marshmello ",
    " Tinashe ",
    " Chanyeol ",
    " Hyolyn ",
    " Tiffany"
  ],
  "Website": [
    "fareastmovement.com"
  ]
}