{
  "title": [
    "Tenth of Tevet"
  ],
  "Official name": [
    "Hebrew:  עשרה בטבת"
  ],
  "Observed by": [
    "Jews"
  ],
  "Type": [
    "Jewish religious, national"
  ],
  "Significance": [
    "Remembers the siege of Jerusalem by Nebuchadnezzar II of Babylonia"
  ],
  "Observances": [
    "Fasting"
  ],
  "Begins": [
    "10 Tevet at 72 minutes before sunrise"
  ],
  "Ends": [
    "at the beginning of 11 Tevet"
  ],
  "2018 date": [
    "December 18, 2018"
  ],
  "2019 date": [
    "January 7,  2020  (rather than in December 2019)"
  ],
  "2020 date": [
    "December 25, 2020"
  ],
  "Frequency": [
    "Annual (per Hebrew Calendar)"
  ]
}