{
    "title": [
        "That Funny Feeling"
    ],
    "Directed by": [
        "Richard Thorpe"
    ],
    "Produced by": [
        "Harry Keller"
    ],
    "Screenplay by": [
        "David R. Schwartz"
    ],
    "Story by": [
        "Norman Barasch , Carroll Moore"
    ],
    "Starring": [
        "Sandra Dee , Bobby Darin"
    ],
    "Music by": [
        "Bobby Darin"
    ],
    "Cinematography": [
        "Clifford Stine"
    ],
    "Edited by": [
        "Gene Milford"
    ],
    "Productioncompany": [
        "Universal Pictures"
    ],
    "Distributed by": [
        "Universal Pictures"
    ],
    "Release date": [
        "August 25, 1965 (1965-08-25) (US)"
    ],
    "Running time": [
        "93 minutes"
    ],
    "Country": [
        "United States"
    ],
    "Language": [
        "English"
    ],
    "Box office": [
        "$1,000,000  (rentals)"
    ]
}