{
  "title": [
    "Fast & Furious"
  ],
  "Directed by": [
    "Justin Lin"
  ],
  "Produced by": [
    "Neal H. Moritz ",
    "Vin Diesel ",
    "Michael Fottrell"
  ],
  "Written by": [
    "Chris Morgan"
  ],
  "Based on": [
    "The Fast and the Furious  by Gary Scott Thompson"
  ],
  "Starring": [
    "Paul Walker ",
    "Vin Diesel ",
    "Michelle Rodriguez ",
    "Jordana Brewster ",
    "Gal Gadot ",
    "Don Omar ",
    "Tego Calderon ",
    "John Ortiz ",
    "Laz Alonso"
  ],
  "Music by": [
    "Brian Tyler"
  ],
  "Cinematography": [
    "Amir Mokri"
  ],
  "Edited by": [
    "Christian Wagner ",
    " Fred Raskin"
  ],
  "Production companies": [
    "Original Film ",
    "Relativity Media ",
    "One Race Films"
  ],
  "Distributed by": [
    "Universal Pictures"
  ],
  "Release date": [
    "March 12, 2009  ( 2009-03-12 )  (Universal CityWalk) ",
    "April 3, 2009  ( 2009-04-03 )  (United States)"
  ],
  "Running time": [
    "107 minutes"
  ],
  "Country": [
    "United States"
  ],
  "Language": [
    "English"
  ],
  "Budget": [
    "$85 million"
  ],
  "Box office": [
    "$363.2 million"
  ]
}