{
    "title": [
        "Demi Moore"
    ],
    "Born": [
        "(1962-11-11) November 11, 1962 (age 56) , Roswell, New Mexico, U.S."
    ],
    "Residence": [
        "Hailey, Idaho, U.S."
    ],
    "Nationality": [
        "American"
    ],
    "Other names": [
        "Demi Gene Guynes"
    ],
    "Occupation": [
        "Actress",
        "film producer",
        "model",
        "songwriter"
    ],
    "Years active": [
        "1981-present"
    ],
    "Spouse(s)": [
        "Freddy Moore , ( m. 1980;  div. 1985)",
        "Bruce Willis , ( m. 1987;  div. 2000)",
        "Ashton Kutcher , ( m. 2005;  div. 2013)"
    ],
    "Children": [
        "3, including Rumer Willis"
    ]
}