{
    "title": [
        "Children of Men"
    ],
    "Directed by": [
        "Alfonso Cuaron"
    ],
    "Produced by": [
        "Hilary Shor",
        "Iain Smith",
        "Tony Smith",
        "Marc Abraham",
        "Eric Newman"
    ],
    "Screenplay by": [
        "Alfonso Cuaron",
        "Timothy J. Sexton",
        "David Arata",
        "Mark Fergus",
        "Hawk Ostby"
    ],
    "Based on": [
        "The Children of Men  , by P. D. James"
    ],
    "Starring": [
        "Clive Owen",
        "Julianne Moore",
        "Clare-Hope Ashitey",
        "Michael Caine",
        "Chiwetel Ejiofor",
        "Pam Ferris",
        "Charlie Hunnam"
    ],
    "Music by": [
        "John Tavener"
    ],
    "Cinematography": [
        "Emmanuel Lubezki"
    ],
    "Edited by": [
        "Alex Rodriguez",
        "Alfonso Cuaron"
    ],
    "Production companies": [
        "Strike Entertainment",
        "Hit and Run Productions"
    ],
    "Distributed by": [
        "Universal Studios"
    ],
    "Release date": [
        "3 September 2006 (2006-09-03) (Venice)",
        "22 September 2006 (2006-09-22) (United Kingdom)",
        "25 December 2006 (2006-12-25) (United States)"
    ],
    "Running time": [
        "109 minutes"
    ],
    "Country": [
        "United Kingdom",
        "United States"
    ],
    "Language": [
        "English"
    ],
    "Budget": [
        "$76 million"
    ],
    "Box office": [
        "$70 million"
    ]
}